kvix/__init__.py
kvix/app.py
kvix/conf.py
kvix/impl.py
kvix/l10n.py
kvix/logo.jpg
kvix/remote.py
kvix/server.py
kvix/stor.py
kvix/util.py
kvix/plugin/__init__.py
kvix/plugin/impl.py
kvix/plugin/builtin/__init__.py
kvix/plugin/builtin/add_action.py
kvix/plugin/builtin/base64decode.py
kvix/plugin/builtin/base64encode.py
kvix/plugin/builtin/calculator.py
kvix/plugin/builtin/edit_action.py
kvix/plugin/builtin/machinist.py
kvix/plugin/builtin/openurl.py
kvix/plugin/builtin/quit.py
kvix/plugin/builtin/settings.py
kvix/plugin/builtin/shell.py
kvix/plugin/builtin/uuid.py
kvix/plugin/builtin/websearch.py
kvix/plugin/discovery/__init__.py
kvix/ui/tray.py
kvix/ui/tk/__init__.py
kvix/ui/tk/plus.py
kvix/ui/tk/util.py
kvix/ui/tk/uni/classic.py
kvix-0.1.3.dist-info/METADATA
kvix-0.1.3.dist-info/WHEEL
kvix-0.1.3.dist-info/entry_points.txt
kvix-0.1.3.dist-info/top_level.txt
kvix-0.1.3.dist-info/RECORD
