Metadata-Version: 2.4
Name: kvix
Version: 0.1.3
Requires-Dist: funcy
Requires-Dist: pynput
Requires-Dist: pystray
Requires-Dist: pygobject
Requires-Dist: pkgconfig
Requires-Dist: pyclip
Requires-Dist: PyYAML
Requires-Dist: Jinja2
